qt_messenger_server-0.0.6.data/scripts/server_run
server/__init__.py
server/server.py
server/common/__init__.py
server/common/descriptors.py
server/common/meta.py
server/common/settings.py
server/common/tcp_socket.py
server/logs/__init__.py
server/logs/logfiles/__init__.py
server/logs/settings/__init__.py
server/logs/settings/colored_formatter.py
server/logs/settings/log_decorator.py
server/logs/settings/socket_logger.py
server/server/__init__.py
server/server/server.py
server/server/server_db.py
server/server/qt/__init__.py
server/server/qt/config_window.py
server/server/qt/history_window.py
server/server/qt/main_window.py
server/server/qt/users_window.py
qt_messenger_server-0.0.6.dist-info/METADATA
qt_messenger_server-0.0.6.dist-info/WHEEL
qt_messenger_server-0.0.6.dist-info/top_level.txt
qt_messenger_server-0.0.6.dist-info/RECORD
