Metadata-Version: 2.1
Name: qt-messenger-server
Version: 0.0.6
Summary: Messenger Server
Home-page: UNKNOWN
Author: Nikuha
Author-email: yoginika@yandex.ru
License: UNKNOWN
Platform: UNKNOWN
Requires-Dist: PyQt5
Requires-Dist: sqlalchemy
Requires-Dist: pycryptodome
Requires-Dist: pycryptodomex
